<?xml version="1.0" encoding="utf-8"?>
<level width="15000" height="600">
    
    <entity x="125" y="25" type="earthPlatform"/>
    <entity x="125" y="75" type="landPlatform"/>
    
    <entity x="325" y="12" type="water"/>
    <entity x="475" y="12" type="water"/>
    <entity x="625" y="12" type="water"/>
    <entity x="305" y="34" type="waterPlatform"/>
    <entity x="550" y="34" type="waterPlatform"/>
    
    <entity x="950" y="25" type="landPlatformLong"/>
    
    <entity x="1275" y="12" type="water"/>
    
    <entity x="1600" y="25" type="earthPlatformLong"/>
    <entity x="1600" y="75" type="landPlatformLong"/>
    <entity x="1825" y="125" type="box"/>
    
    <entity x="1925" y="12" type="water"/>
    <entity x="2075" y="12" type="water"/>
    <entity x="2225" y="12" type="water"/>
    <entity x="2075" y="162" type="airPlatform"/>
    
    <entity x="2550" y="25" type="earthPlatformLong"/>
    <entity x="2550" y="75" type="landPlatformLong"/>
    <entity x="2825" y="86" type="grassHalfRight"/>
    <entity x="2825" y="125" type="box"/>
    
    <entity x="2875" y="12" type="water"/>
    <entity x="3025" y="12" type="water"/>
    
    <entity x="3075" y="36" type="grassHalfLeft"/>
    
    <entity x="3350" y="25" type="earthPlatformLong"/>
    <entity x="3350" y="75" type="darkEarthPlatformLong"/>
    <entity x="3350" y="125" type="darkEarthPlatformLong"/>
    <entity x="3350" y="175" type="earthPlatformLong"/>
    <entity x="3350" y="225" type="landPlatformLong"/>
    
    <entity x="3675" y="12" type="water"/>
    <entity x="3825" y="12" type="water"/>
    <entity x="3975" y="12" type="water"/>
    <entity x="3650" y="34" type="waterPlatform"/>
    <entity x="3900" y="34" type="waterPlatform"/>
    
    <entity x="4175" y="25" type="earthPlatform"/>
    <entity x="4175" y="75" type="landPlatform"/>
    <entity x="4425" y="25" type="earthPlatform"/>
    <entity x="4800" y="25" type="earthPlatformLong"/>
    <entity x="4800" y="75" type="landPlatformLong"/>
    <entity x="4250" y="125" type="box"/>
    <entity x="4300" y="125" type="box"/>
    <entity x="4325" y="175" type="box"/>
    <entity x="4335" y="67" type="spike"/>
    <entity x="4435" y="67" type="spike"/>
    <entity x="4515" y="67" type="spike"/>
    <entity x="5125" y="12" type="water"/>
    <entity x="5275" y="12" type="water"/>
    <entity x="5200" y="110" type="bridge"/>
    <entity x="5600" y="25" type="earthPlatformLong"/>
    <entity x="5600" y="75" type="landPlatformLong"/>
    <entity x="5925" y="12" type="water"/>
    
    <entity x="6075" y="25" type="earthPlatformShort"/>
    <entity x="6075" y="75" type="landPlatformShort"/>
    
    <entity x="6225" y="12" type="water"/>
    <entity x="6375" y="12" type="water"/>
    <entity x="6250" y="34" type="waterPlatform"/>
    
    <entity x="6700" y="25" type="earthPlatformLong"/>
    <entity x="6700" y="75" type="darkEarthPlatformLong"/>
    <entity x="6700" y="125" type="darkEarthPlatformLong"/>
    <entity x="6700" y="175" type="landPlatformLong"/>
    <entity x="7025" y="12" type="water"/>
    <entity x="7175" y="12" type="water"/>
    <entity x="7015" y="34" type="waterPlatform"/>
    
    <entity x="7500" y="25" type="landPlatformLong"/>
    <entity x="7825" y="12" type="water"/>
    
    <entity x="8150" y="25" type="landPlatformLong"/>
    <entity x="8075" y="75" type="box"/>
    <entity x="8125" y="75" type="box"/>
    <entity x="8175" y="75" type="box"/>
    <entity x="8225" y="75" type="box"/>
    <entity x="8275" y="75" type="box"/>
    <entity x="8325" y="75" type="box"/>
    <entity x="8375" y="75" type="box"/>
    <entity x="8225" y="125" type="box"/>
    <entity x="8275" y="125" type="box"/>
    <entity x="8325" y="125" type="box"/>
    <entity x="8375" y="125" type="box"/>
    <entity x="8325" y="175" type="box"/>
    <entity x="8375" y="175" type="box"/>
    
    <entity x="8475" y="12" type="water"/>
    <entity x="8625" y="12" type="water"/>
    <entity x="8775" y="12" type="water"/>
    <entity x="8650" y="34" type="waterPlatform"/>
    
    <entity x="9100" y="25" type="landPlatformLong"/>
    
    <entity x="9425" y="12" type="water"/>
    <entity x="9575" y="12" type="water"/>
    <entity x="9525" y="87" type="airPlatform"/>
    
    <entity x="9900" y="25" type="earthPlatformLong"/>
    <entity x="9900" y="75" type="earthPlatformLong"/>
    <entity x="9900" y="125" type="landPlatformLong"/>
    
    <entity x="10225" y="12" type="water"/>
    <entity x="10375" y="12" type="water"/>
    <entity x="10525" y="12" type="water"/>
    <entity x="10675" y="12" type="water"/>
    <entity x="10825" y="12" type="water"/>
    <entity x="10975" y="12" type="water"/>
    <entity x="11125" y="12" type="water"/>
    <entity x="11275" y="12" type="water"/>
    <entity x="11425" y="12" type="water"/>
    <entity x="11575" y="12" type="water"/>
    <entity x="11725" y="12" type="water"/>
    <entity x="11875" y="12" type="water"/>
    
    <entity x="10375" y="187" type="airPlatformLong"/>
    <entity x="10775" y="112" type="airPlatformLong"/>
    <entity x="11075" y="67" type="airPlatform"/>
    <entity x="11375" y="112" type="airPlatformLong"/>
    <entity x="11775" y="112" type="airPlatformLong"/>
    
    <entity x="12025" y="25" type="earthPlatformShort"/>
    <entity x="12025" y="75" type="landPlatformShort"/>
    
    <entity x="12175" y="12" type="water"/>
    
    <entity x="12500" y="25" type="earthPlatformLong"/>
    <entity x="12500" y="75" type="landPlatformLong"/>
    <entity x="12825" y="12" type="water"/>
    
    <entity x="13025" y="25" type="earthPlatform"/>
    <entity x="13025" y="75" type="landPlatform"/>
    <entity x="13275" y="25" type="earthPlatform"/>
    <entity x="13525" y="25" type="earthPlatform"/>
    <entity x="13525" y="75" type="landPlatform"/>
    <entity x="13125" y="125" type="box"/>
    <entity x="13150" y="175" type="box"/>
    <entity x="13185" y="67" type="spike"/>
    <entity x="13285" y="67" type="spike"/>
    <entity x="13365" y="67" type="spike"/>
    
    <entity x="13725" y="12" type="water"/>
    <entity x="13875" y="12" type="water"/>
    <entity x="14025" y="12" type="water"/>
    <entity x="14175" y="12" type="water"/>
    <entity x="14325" y="12" type="water"/>
    <entity x="14475" y="12" type="water"/>
    
    <entity x="13800" y="34" type="waterPlatform"/>
    <entity x="14050" y="34" type="waterPlatform"/>
    <entity x="14300" y="34" type="waterPlatform"/>
    
    <entity x="14750" y="75" type="landPlatformLong"/>
    
    
    <entity x="3679" y="90" type="potion"/>
    <entity x="7005" y="177" type="antidote"/>
    
    <entity x="15" y="100" type="player"/>
        
    <entity x="14928" y="115" type="tent"/>
</level>
